AUTHORS
ChangeLog
LICENSE
MANIFEST.in
README
distribute_setup.py
setup.py
stagger/__init__.py
stagger/commandline.py
stagger/conversion.py
stagger/errors.py
stagger/fileutil.py
stagger/frames.py
stagger/id3.py
stagger/id3v1.py
stagger/specs.py
stagger/tags.py
stagger/util.py
stagger.egg-info/PKG-INFO
stagger.egg-info/SOURCES.txt
stagger.egg-info/dependency_links.txt
stagger.egg-info/entry_points.txt
stagger.egg-info/top_level.txt
test/__init__.py
test/alltests.py
test/conversion.py
test/fileutil.py
test/friendly.py
test/id3v1.py
test/id3v1_fileop.py
test/samples.py
test/specs.py
test/tag.py
test/samples/22.itunes.astronomycast.id3
test/samples/22.itunes.rvad.id3
test/samples/22.itunes.sample.id3
test/samples/22.unknown.coulton-song.id3
test/samples/23.itunes.astronomycast-conversion.id3
test/samples/23.itunes.conversion.id3
test/samples/23.synthetic.empty-extended-header.lossy.id3
test/samples/23.synthetic.extended-header-bad-crc.lossy.id3
test/samples/23.unknown.RGAD-frame.id3
test/samples/23.unknown.ea-promo-soundtrack.id3
test/samples/23.unknown.zero-length-frames.id3
test/samples/23.windows-vista-explorer.all-fields-test.id3
test/samples/23.windows-vista-explorer.sample.id3
test/samples/24.MusicBrainz.XSOP-frame.id3
test/samples/24.issue35.rioport.status-flag.id3
test/samples/24.issue37.stagger.duplicate-talb.id3
test/samples/24.itunes.8bit-frame-size.id3
test/samples/24.itunes.astronomycast-conversion.id3
test/samples/24.itunes.conversion.id3
test/samples/24.itunes.ea-promo-soundtrack-conversion.id3
test/samples/24.lame.TTSE-frame.id3
test/samples/24.stagger.empty-strings.id3
test/samples/24.stagger.sample-01.id3
test/samples/24.taglib.invalid-unsynch.id3
test/samples/24.unknown.NCON-frame.id3
test/samples/24.unknown.empty.frames.id3
test/samples/cover.jpg
test/samples/cover2.jpg